[
    {
        "key": "dbln",
        "value": "%7B%2261565919872526%22%3A%22iJQJa2Di%22%2C%2261565929778268%22%3A%22JMHKb8Qq%22%2C%22100001515792626%22%3A%2253Fjkvbz%22%2C%22100004557907080%22%3A%22ZnVaFA3Y%22%7D",
        "domain": "facebook.com",
        "path": "/login/device-based/",
        "hostOnly": false,
        "creation": "2024-10-24T01:29:57.638Z",
        "lastAccessed": "2024-10-24T01:29:57.639Z"
    },
    {
        "key": "datr",
        "value": "wEAOZx5qFM3K8UxuHPsLDe3J",
        "domain": "facebook.com",
        "path": "/",
        "hostOnly": false,
        "creation": "2024-10-24T01:29:57.639Z",
        "lastAccessed": "2024-10-24T01:29:57.639Z"
    },
    {
        "key": "sb",
        "value": "wEAOZzGxG5GPm0VQ0Wbc8GKv",
        "domain": "facebook.com",
        "path": "/",
        "hostOnly": false,
        "creation": "2024-10-24T01:29:57.639Z",
        "lastAccessed": "2024-10-24T01:29:57.639Z"
    },
    {
        "key": "ps_l",
        "value": "1",
        "domain": "facebook.com",
        "path": "/",
        "hostOnly": false,
        "creation": "2024-10-24T01:29:57.639Z",
        "lastAccessed": "2024-10-24T01:29:57.639Z"
    },
    {
        "key": "ps_n",
        "value": "1",
        "domain": "facebook.com",
        "path": "/",
        "hostOnly": false,
        "creation": "2024-10-24T01:29:57.639Z",
        "lastAccessed": "2024-10-24T01:29:57.639Z"
    },
    {
        "key": "dpr",
        "value": "1.0840239524841309",
        "domain": "facebook.com",
        "path": "/",
        "hostOnly": false,
        "creation": "2024-10-24T01:29:57.640Z",
        "lastAccessed": "2024-10-24T01:29:57.640Z"
    },
    {
        "key": "vpd",
        "value": "v1%3B590x377x1.0840239524841309",
        "domain": "facebook.com",
        "path": "/",
        "hostOnly": false,
        "creation": "2024-10-24T01:29:57.640Z",
        "lastAccessed": "2024-10-24T01:29:57.640Z"
    },
    {
        "key": "wd",
        "value": "444x695",
        "domain": "facebook.com",
        "path": "/",
        "hostOnly": false,
        "creation": "2024-10-24T01:29:57.640Z",
        "lastAccessed": "2024-10-24T01:29:57.640Z"
    },
    {
        "key": "c_user",
        "value": "100004557907080",
        "domain": "facebook.com",
        "path": "/",
        "hostOnly": false,
        "creation": "2024-10-24T01:29:57.640Z",
        "lastAccessed": "2024-10-24T01:29:57.640Z"
    },
    {
        "key": "fr",
        "value": "0Xx8cTYpygvjXRIFn.AWVbO5Asns9-Mr_vikU6j0_TwqM.BnDkDA..AAA.0.0.BnGZks.AWVWAttLqyQ",
        "domain": "facebook.com",
        "path": "/",
        "hostOnly": false,
        "creation": "2024-10-24T01:29:57.640Z",
        "lastAccessed": "2024-10-24T01:29:57.640Z"
    },
    {
        "key": "xs",
        "value": "16%3Afaugk9BaUcmXvg%3A2%3A1729730861%3A-1%3A13739",
        "domain": "facebook.com",
        "path": "/",
        "hostOnly": false,
        "creation": "2024-10-24T01:29:57.640Z",
        "lastAccessed": "2024-10-24T01:29:57.640Z"
    },
    {
        "key": "locale",
        "value": "th_TH",
        "domain": "facebook.com",
        "path": "/",
        "hostOnly": false,
        "creation": "2024-10-24T01:29:57.640Z",
        "lastAccessed": "2024-10-24T01:29:57.640Z"
    },
    {
        "key": "fbl_st",
        "value": "101437241%3BT%3A28828889",
        "domain": "facebook.com",
        "path": "/",
        "hostOnly": false,
        "creation": "2024-10-24T01:29:57.640Z",
        "lastAccessed": "2024-10-24T01:29:57.640Z"
    },
    {
        "key": "wl_cbv",
        "value": "v2%3Bclient_version%3A2655%3Btimestamp%3A1729733376",
        "domain": "facebook.com",
        "path": "/",
        "hostOnly": false,
        "creation": "2024-10-24T01:29:57.640Z",
        "lastAccessed": "2024-10-24T01:29:57.640Z"
    }
        ]
